{"name":"Smart Collaboration","tagline":"Another Fine Summer Project by the MIT Human Dynamics Lab Computational Law Research and Development","body":"## Goal\r\nWe want to be able to collect collaboration signals for hackathons by building an online hackathon tool that supports project workspaces.  During work this spring we built the basic framework for project disclosure, reviews,  and event summarization but in order to obtain data on individual and project performance as well as group collaboration we would need workspaces that support online meetings (Google Hangouts), chat (IRC), and code (git and pull request discussions).  \r\n\r\nThis would focus effort directly on running hackathons that are completely virtual rather than the in person hackathons that are currently supported by applications.  However, for this summer some of the core functionality that would need to be present for large-scale deployment (dynamic scheduling, initial project vetting, and team formation recommendations) would not be a top priority. The focus would be on prototyping the tools for collecting and analysing the data on collaboration from the workspace. \r\n\r\nThe long-term goal of this effort is triggering system processes for automated resource allocation and collaboration at large scale.\r\n\r\nKeywords: \r\nhackathons, \r\ngroup \r\ndynamics, \r\nmicrotasking \r\n\r\n## Schedule\r\n\r\n We’ll be looking at syncing up weekly. \r\n\r\n* Start of September should have the core systems in place for monitoring collaboration signals in Google Hangouts\r\n* Start of October should see operationalized systems for persisting collaboration data as well as visualization\r\n* CALIHack 2016 next spring is tentatively set as the first large-scale online hackathon that would use the tool\r\n* Smaller hackathons, including  \r\n\r\n[tbd]\r\n\r\n## Scope\r\n\r\nCreate Personal Identity Accounts with OAuth2\r\n\r\nCreate Project Workspaces (Google Hangouts, GitHub, chat)\r\n\r\nModels supporting online hackathon: User, Event, Workspace, Project, Role, Rating\r\n\r\nTwitter Ratings\r\n\r\nCreate Event scheduling\r\n\r\nPrepare Collaboration Analytics \r\n\r\nInvolve external groups in collecting feedback verify Collaboration Analytics\r\n\r\nCoordinate with Google, GitHub, and Slack to estimate scaling of the workspaces\r\n\r\nSupport analytics that are tied to a Personal Data Service (owner labels on collaboration signals)\r\n","google":"","note":"Don't delete this file! It's used internally to help with page regeneration."}